Metadata-Version: 1.0
Name: sphinx-fortran
Version: 1.0.1
Summary: Fortran domain and autodoc extensions to Sphinx
Home-page: http://sphinx-fortran.readthedocs.org
Author: Stephane Raynaud
Author-email: stephane.raynaud@gmail.com
License: CeCiLL-A
Platform: UNKNOWN
